azure/__init__.py
azure/cli/__init__.py
azure/cli/command_modules/__init__.py
azure/cli/command_modules/ams/__init__.py
azure/cli/command_modules/ams/_client_factory.py
azure/cli/command_modules/ams/_completers.py
azure/cli/command_modules/ams/_exception_handler.py
azure/cli/command_modules/ams/_format.py
azure/cli/command_modules/ams/_help.py
azure/cli/command_modules/ams/_params.py
azure/cli/command_modules/ams/_sdk_utils.py
azure/cli/command_modules/ams/_test_utils.py
azure/cli/command_modules/ams/_utils.py
azure/cli/command_modules/ams/_validators.py
azure/cli/command_modules/ams/commands.py
azure/cli/command_modules/ams/operations/__init__.py
azure/cli/command_modules/ams/operations/account.py
azure/cli/command_modules/ams/operations/account_filter.py
azure/cli/command_modules/ams/operations/asset.py
azure/cli/command_modules/ams/operations/asset_filter.py
azure/cli/command_modules/ams/operations/content_key_policy.py
azure/cli/command_modules/ams/operations/job.py
azure/cli/command_modules/ams/operations/live_event.py
azure/cli/command_modules/ams/operations/live_output.py
azure/cli/command_modules/ams/operations/mru.py
azure/cli/command_modules/ams/operations/sp.py
azure/cli/command_modules/ams/operations/streaming_endpoint.py
azure/cli/command_modules/ams/operations/streaming_locator.py
azure/cli/command_modules/ams/operations/streaming_policy.py
azure/cli/command_modules/ams/operations/transform.py
opal_azure_cli_ams-0.4.10.dist-info/METADATA
opal_azure_cli_ams-0.4.10.dist-info/WHEEL
opal_azure_cli_ams-0.4.10.dist-info/top_level.txt
opal_azure_cli_ams-0.4.10.dist-info/RECORD
